ai_debate_chat/__init__.py
ai_debate_chat/debate_chat.py
ai_debate_chat/ml_pipeline_langchain.py
ai_debate_chat-0.1.1.dist-info/licenses/LICENSE
ai_debate_chat-0.1.1.dist-info/METADATA
ai_debate_chat-0.1.1.dist-info/WHEEL
ai_debate_chat-0.1.1.dist-info/top_level.txt
ai_debate_chat-0.1.1.dist-info/RECORD
